UnityPyLive2DExtractor/__init__.py
UnityPyLive2DExtractor/__main__.py
UnityPyLive2DExtractor/generated/__init__.py
unitypylive2dextractor-0.2.2.dist-info/METADATA
unitypylive2dextractor-0.2.2.dist-info/WHEEL
unitypylive2dextractor-0.2.2.dist-info/entry_points.txt
unitypylive2dextractor-0.2.2.dist-info/top_level.txt
unitypylive2dextractor-0.2.2.dist-info/RECORD
