Metadata-Version: 2.4
Name: UnityPyLive2DExtractor
Version: 0.2.2
Summary: General purpose, single-file Unity Live2D Asset recovery tool
Home-page: https://github.com/mos9527/UnityPyLive2DExtractor
Author: greats3an
Author-email: greats3an@gmail.com
Classifier: Programming Language :: Python :: 3
Classifier: License :: OSI Approved :: Apache Software License
Classifier: Operating System :: OS Independent
Requires-Python: >=3.10
Requires-Dist: sssekai>=0.7.12
Dynamic: author
Dynamic: author-email
Dynamic: classifier
Dynamic: description
Dynamic: description-content-type
Dynamic: home-page
Dynamic: requires-dist
Dynamic: requires-python
Dynamic: summary
